README.md
setup.py
HomoglyphsCJK/__init__.py
HomoglyphsCJK/hg_functions.py
HomoglyphsCJK/test_run.py
HomoglyphsCJK.egg-info/PKG-INFO
HomoglyphsCJK.egg-info/SOURCES.txt
HomoglyphsCJK.egg-info/dependency_links.txt
HomoglyphsCJK.egg-info/requires.txt
HomoglyphsCJK.egg-info/top_level.txt