Metadata-Version: 2.1
Name: HomoglyphsCJK
Version: 0.1.3
Summary: An easy Python package for fuzzy matching Chinese(simplified and traditional), Japanese and Korean, using character similarity trained from ViT transformer
Home-page: https://github.com/dell-research-harvard/HomoglyphsCJK.git
Author: HomoglyphsCJK Team
Author-email: homoglyphscjk@gmail.com
Classifier: Programming Language :: Python :: 3
Classifier: License :: OSI Approved :: MIT License
Classifier: Operating System :: OS Independent
